logthing/__init__.py
logthing/srothandler.py
logthing/utils.py
logthing-1.0.0.dist-info/LICENSE
logthing-1.0.0.dist-info/METADATA
logthing-1.0.0.dist-info/WHEEL
logthing-1.0.0.dist-info/top_level.txt
logthing-1.0.0.dist-info/RECORD
